coboljsonifier/__init__.py
coboljsonifier/copybookextractor.py
coboljsonifier/parser.py
coboljsonifier/config/__init__.py
coboljsonifier/config/parser_type_enum.py
coboljsonifier/extractors/__init__.py
coboljsonifier/extractors/book_item.py
coboljsonifier/extractors/field_extractor.py
coboljsonifier/extractors/structure_extractor.py
coboljsonifier/extractors/subformat_extractor.py
coboljsonifier/fields/__init__.py
coboljsonifier/fields/field.py
coboljsonifier/fields/field_alphanumeric_ascii.py
coboljsonifier/fields/field_alphanumeric_ebcdic.py
coboljsonifier/fields/field_array.py
coboljsonifier/fields/field_group.py
coboljsonifier/fields/field_numeric_ascii.py
coboljsonifier/fields/field_numeric_binary.py
coboljsonifier/fields/field_numeric_comp3.py
coboljsonifier/fields/field_numeric_ebcdic.py
coboljsonifier/fields/field_numeric_masked_ascii.py
coboljsonifier/fields/field_wrapper.py
coboljsonifier-1.0.8.dist-info/METADATA
coboljsonifier-1.0.8.dist-info/WHEEL
coboljsonifier-1.0.8.dist-info/top_level.txt
coboljsonifier-1.0.8.dist-info/RECORD
