Metadata-Version: 2.4
Name: coboljsonifier
Version: 1.0.8
Summary: Convert cobol copybook to Json and parse data files based on it
Home-page: https://github.com/jrperin/cobol-copybook.jsonifier
Author: Joao Roberto Perin
License-Expression: MIT
Project-URL: Homepage, https://github.com/jrperin/cobol-copybook.jsonifier
Project-URL: Issues, https://github.com/jrperin/cobol-copybook.jsonifier/issues
Keywords: Cobol,Json,Mainframe,Copybook,Cobol & JSON
Classifier: Programming Language :: Python
Requires-Python: >=3.7
